npd_entropy/__init__.py
npd_entropy/npd_entropy.py
npd_entropy-0.3.dist-info/METADATA
npd_entropy-0.3.dist-info/WHEEL
npd_entropy-0.3.dist-info/top_level.txt
npd_entropy-0.3.dist-info/RECORD
